{
  "memory": [
    {
      "seq_len": 1024,
      "k": 8,
      "d_model": 512,
      "n_heads": 8,
      "batch_size": 1,
      "std_memory": 106.6357421875,
      "topk_memory": 74.5751953125,
      "theoretical_reduction": 10.76923076923077,
      "actual_reduction": 1.4299089897204216,
      "memory_ratio": 0.6993452081139246
    },
    {
      "seq_len": 1024,
      "k": 16,
      "d_model": 512,
      "n_heads": 8,
      "batch_size": 1,
      "std_memory": 106.6357421875,
      "topk_memory": 107.4501953125,
      "theoretical_reduction": 10.0,
      "actual_reduction": 0.9924201801343282,
      "memory_ratio": 1.0076377123494666
    },
    {
      "seq_len": 1024,
      "k": 32,
      "d_model": 512,
      "n_heads": 8,
      "batch_size": 1,
      "std_memory": 106.6357421875,
      "topk_memory": 173.2001953125,
      "theoretical_reduction": 8.75,
      "actual_reduction": 0.6156791104946521,
      "memory_ratio": 1.6242227208205504
    },
    {
      "seq_len": 1024,
      "k": 64,
      "d_model": 512,
      "n_heads": 8,
      "batch_size": 1,
      "std_memory": 106.6357421875,
      "topk_memory": 304.7001953125,
      "theoretical_reduction": 7.0,
      "actual_reduction": 0.3499693923009618,
      "memory_ratio": 2.857392737762718
    },
    {
      "seq_len": 1024,
      "k": 128,
      "d_model": 512,
      "n_heads": 8,
      "batch_size": 1,
      "std_memory": 106.6357421875,
      "topk_memory": 567.7001953125,
      "theoretical_reduction": 5.0,
      "actual_reduction": 0.18783812841353803,
      "memory_ratio": 5.3237327716470535
    },
    {
      "seq_len": 1024,
      "k": 256,
      "d_model": 512,
      "n_heads": 8,
      "batch_size": 1,
      "std_memory": 106.6357421875,
      "topk_memory": 1093.7001953125,
      "theoretical_reduction": 3.1818181818181817,
      "actual_reduction": 0.09749997544531046,
      "memory_ratio": 10.256412839415724
    },
    {
      "seq_len": 2048,
      "k": 8,
      "d_model": 512,
      "n_heads": 8,
      "batch_size": 1,
      "std_memory": 375.6357421875,
      "topk_memory": 102.5751953125,
      "theoretical_reduction": 20.615384615384617,
      "actual_reduction": 3.6620524196235613,
      "memory_ratio": 0.2730709136333975
    },
    {
      "seq_len": 2048,
      "k": 16,
      "d_model": 512,
      "n_heads": 8,
      "batch_size": 1,
      "std_memory": 375.6357421875,
      "topk_memory": 135.4501953125,
      "theoretical_reduction": 19.142857142857142,
      "actual_reduction": 2.773238837499369,
      "memory_ratio": 0.3605892094392059
    },
    {
      "seq_len": 2048,
      "k": 32,
      "d_model": 512,
      "n_heads": 8,
      "batch_size": 1,
      "std_memory": 375.6357421875,
      "topk_memory": 201.2001953125,
      "theoretical_reduction": 16.75,
      "actual_reduction": 1.8669750374947216,
      "memory_ratio": 0.5356258010508227
    },
    {
      "seq_len": 2048,
      "k": 64,
      "d_model": 512,
      "n_heads": 8,
      "batch_size": 1,
      "std_memory": 375.6357421875,
      "topk_memory": 332.7001953125,
      "theoretical_reduction": 13.4,
      "actual_reduction": 1.1290517633591148,
      "memory_ratio": 0.8856989842740562
    },
    {
      "seq_len": 2048,
      "k": 128,
      "d_model": 512,
      "n_heads": 8,
      "batch_size": 1,
      "std_memory": 375.6357421875,
      "topk_memory": 595.7001953125,
      "theoretical_reduction": 9.571428571428571,
      "actual_reduction": 0.6305785110418576,
      "memory_ratio": 1.5858453507205232
    },
    {
      "seq_len": 2048,
      "k": 256,
      "d_model": 512,
      "n_heads": 8,
      "batch_size": 1,
      "std_memory": 375.6357421875,
      "topk_memory": 1121.7001953125,
      "theoretical_reduction": 6.090909090909091,
      "actual_reduction": 0.3348806960694607,
      "memory_ratio": 2.9861380836134575
    },
    {
      "seq_len": 4096,
      "k": 8,
      "d_model": 512,
      "n_heads": 8,
      "batch_size": 1,
      "std_memory": 1441.6357421875,
      "topk_memory": 183.7001953125,
      "theoretical_reduction": 40.30769230769231,
      "actual_reduction": 7.847763796522229,
      "memory_ratio": 0.12742483412193858
    },
    {
      "seq_len": 4096,
      "k": 16,
      "d_model": 512,
      "n_heads": 8,
      "batch_size": 1,
      "std_memory": 1441.6357421875,
      "topk_memory": 187.4501953125,
      "theoretical_reduction": 37.42857142857143,
      "actual_reduction": 7.690766818269436,
      "memory_ratio": 0.13002604598861292
    },
    {
      "seq_len": 4096,
      "k": 32,
      "d_model": 512,
      "n_heads": 8,
      "batch_size": 1,
      "std_memory": 1441.6357421875,
      "topk_memory": 253.2001953125,
      "theoretical_reduction": 32.75,
      "actual_reduction": 5.693659676716408,
      "memory_ratio": 0.17563396071763643
    },
    {
      "seq_len": 4096,
      "k": 64,
      "d_model": 512,
      "n_heads": 8,
      "batch_size": 1,
      "std_memory": 1441.6357421875,
      "topk_memory": 384.7001953125,
      "theoretical_reduction": 26.2,
      "actual_reduction": 3.747426592847007,
      "memory_ratio": 0.2668497901756834
    },
    {
      "seq_len": 4096,
      "k": 128,
      "d_model": 512,
      "n_heads": 8,
      "batch_size": 1,
      "std_memory": 1441.6357421875,
      "topk_memory": 647.7001953125,
      "theoretical_reduction": 18.714285714285715,
      "actual_reduction": 2.2257762968435495,
      "memory_ratio": 0.4492814490917774
    },
    {
      "seq_len": 4096,
      "k": 256,
      "d_model": 512,
      "n_heads": 8,
      "batch_size": 1,
      "std_memory": 1441.6357421875,
      "topk_memory": 1173.7001953125,
      "theoretical_reduction": 11.909090909090908,
      "actual_reduction": 1.2282827828989682,
      "memory_ratio": 0.8141447669239653
    },
    {
      "seq_len": 8192,
      "k": 8,
      "d_model": 512,
      "n_heads": 8,
      "batch_size": 1,
      "std_memory": 5685.6357421875,
      "topk_memory": 351.7001953125,
      "theoretical_reduction": 79.6923076923077,
      "actual_reduction": 16.166143260556282,
      "memory_ratio": 0.06185767278457173
    },
    {
      "seq_len": 8192,
      "k": 16,
      "d_model": 512,
      "n_heads": 8,
      "batch_size": 1,
      "std_memory": 5685.6357421875,
      "topk_memory": 351.7001953125,
      "theoretical_reduction": 74.0,
      "actual_reduction": 16.166143260556282,
      "memory_ratio": 0.06185767278457173
    },
    {
      "seq_len": 8192,
      "k": 32,
      "d_model": 512,
      "n_heads": 8,
      "batch_size": 1,
      "std_memory": 5685.6357421875,
      "topk_memory": 357.2001953125,
      "theoretical_reduction": 64.75,
      "actual_reduction": 15.917224617453995,
      "memory_ratio": 0.06282502283114434
    },
    {
      "seq_len": 8192,
      "k": 64,
      "d_model": 512,
      "n_heads": 8,
      "batch_size": 1,
      "std_memory": 5685.6357421875,
      "topk_memory": 488.7001953125,
      "theoretical_reduction": 51.8,
      "actual_reduction": 11.634199856523104,
      "memory_ratio": 0.08595348303556231
    },
    {
      "seq_len": 8192,
      "k": 128,
      "d_model": 512,
      "n_heads": 8,
      "batch_size": 1,
      "std_memory": 5685.6357421875,
      "topk_memory": 751.7001953125,
      "theoretical_reduction": 37.0,
      "actual_reduction": 7.563701296929747,
      "memory_ratio": 0.13221040344439824
    },
    {
      "seq_len": 8192,
      "k": 256,
      "d_model": 512,
      "n_heads": 8,
      "batch_size": 1,
      "std_memory": 5685.6357421875,
      "topk_memory": 1277.7001953125,
      "theoretical_reduction": 23.545454545454547,
      "actual_reduction": 4.449898155331272,
      "memory_ratio": 0.2247242442620701
    }
  ],
  "speed": [
    {
      "seq_len": 1024,
      "k": 8,
      "d_model": 512,
      "n_heads": 8,
      "batch_size": 1,
      "std_time": 0.0005294746822781032,
      "std_time_std": 1.339494297142145e-05,
      "topk_time": 0.0008108086056179471,
      "topk_time_std": 1.7825596886205636e-05,
      "speedup": 0.6530205508543796,
      "time_ratio": 1.5313453744934211
    },
    {
      "seq_len": 1024,
      "k": 16,
      "d_model": 512,
      "n_heads": 8,
      "batch_size": 1,
      "std_time": 0.0005294746822781032,
      "std_time_std": 1.339494297142145e-05,
      "topk_time": 0.0008585717942979601,
      "topk_time_std": 6.994696293796637e-05,
      "speedup": 0.6166923788954025,
      "time_ratio": 1.6215540101065697
    },
    {
      "seq_len": 1024,
      "k": 32,
      "d_model": 512,
      "n_heads": 8,
      "batch_size": 1,
      "std_time": 0.0005294746822781032,
      "std_time_std": 1.339494297142145e-05,
      "topk_time": 0.0008104377322726779,
      "topk_time_std": 5.327382728452797e-06,
      "speedup": 0.6533193867878272,
      "time_ratio": 1.5306449191974787
    },
    {
      "seq_len": 1024,
      "k": 64,
      "d_model": 512,
      "n_heads": 8,
      "batch_size": 1,
      "std_time": 0.0005294746822781032,
      "std_time_std": 1.339494297142145e-05,
      "topk_time": 0.000831445058186849,
      "topk_time_std": 1.907227212078726e-05,
      "speedup": 0.6368125916013507,
      "time_ratio": 1.5703207084604998
    },
    {
      "seq_len": 1024,
      "k": 128,
      "d_model": 512,
      "n_heads": 8,
      "batch_size": 1,
      "std_time": 0.0005294746822781032,
      "std_time_std": 1.339494297142145e-05,
      "topk_time": 0.0008361869388156467,
      "topk_time_std": 2.998485708404824e-05,
      "speedup": 0.6332013305876761,
      "time_ratio": 1.579276529744334
    },
    {
      "seq_len": 2048,
      "k": 8,
      "d_model": 512,
      "n_heads": 8,
      "batch_size": 1,
      "std_time": 0.0005328655242919922,
      "std_time_std": 1.8708503103025126e-05,
      "topk_time": 0.001294533411661784,
      "topk_time_std": 0.00012505247451448284,
      "speedup": 0.4116274786665848,
      "time_ratio": 2.4293810589112605
    },
    {
      "seq_len": 2048,
      "k": 16,
      "d_model": 512,
      "n_heads": 8,
      "batch_size": 1,
      "std_time": 0.0005328655242919922,
      "std_time_std": 1.8708503103025126e-05,
      "topk_time": 0.001127057605319553,
      "topk_time_std": 3.084259216761419e-05,
      "speedup": 0.47279351275120457,
      "time_ratio": 2.1150882426050215
    },
    {
      "seq_len": 2048,
      "k": 32,
      "d_model": 512,
      "n_heads": 8,
      "batch_size": 1,
      "std_time": 0.0005328655242919922,
      "std_time_std": 1.8708503103025126e-05,
      "topk_time": 0.001132223341200087,
      "topk_time_std": 1.076171948113207e-05,
      "speedup": 0.4706364061768834,
      "time_ratio": 2.124782500621427
    },
    {
      "seq_len": 2048,
      "k": 64,
      "d_model": 512,
      "n_heads": 8,
      "batch_size": 1,
      "std_time": 0.0005328655242919922,
      "std_time_std": 1.8708503103025126e-05,
      "topk_time": 0.0011521710289849173,
      "topk_time_std": 4.461641230598614e-05,
      "speedup": 0.4624882164946084,
      "time_ratio": 2.1622172508078545
    },
    {
      "seq_len": 2048,
      "k": 128,
      "d_model": 512,
      "n_heads": 8,
      "batch_size": 1,
      "std_time": 0.0005328655242919922,
      "std_time_std": 1.8708503103025126e-05,
      "topk_time": 0.0012404123942057292,
      "topk_time_std": 4.628355429522949e-05,
      "speedup": 0.42958739108149663,
      "time_ratio": 2.3278150633855335
    },
    {
      "seq_len": 4096,
      "k": 8,
      "d_model": 512,
      "n_heads": 8,
      "batch_size": 1,
      "std_time": 0.0005357530381944444,
      "std_time_std": 2.2069651137468503e-05,
      "topk_time": 0.0018064445919460722,
      "topk_time_std": 5.492294657093695e-05,
      "speedup": 0.2965787273980437,
      "time_ratio": 3.3717859968354436
    },
    {
      "seq_len": 4096,
      "k": 16,
      "d_model": 512,
      "n_heads": 8,
      "batch_size": 1,
      "std_time": 0.0005357530381944444,
      "std_time_std": 2.2069651137468503e-05,
      "topk_time": 0.0017255412207709418,
      "topk_time_std": 6.843080359871146e-06,
      "speedup": 0.31048405668053486,
      "time_ratio": 3.2207772943037978
    },
    {
      "seq_len": 4096,
      "k": 32,
      "d_model": 512,
      "n_heads": 8,
      "batch_size": 1,
      "std_time": 0.0005357530381944444,
      "std_time_std": 2.2069651137468503e-05,
      "topk_time": 0.0017193158467610676,
      "topk_time_std": 1.219712071424169e-05,
      "speedup": 0.31160827093155835,
      "time_ratio": 3.209157436708861
    },
    {
      "seq_len": 4096,
      "k": 64,
      "d_model": 512,
      "n_heads": 8,
      "batch_size": 1,
      "std_time": 0.0005357530381944444,
      "std_time_std": 2.2069651137468503e-05,
      "topk_time": 0.0018409623040093316,
      "topk_time_std": 3.851001087870497e-05,
      "speedup": 0.29101792960543355,
      "time_ratio": 3.4362143987341778
    },
    {
      "seq_len": 4096,
      "k": 128,
      "d_model": 512,
      "n_heads": 8,
      "batch_size": 1,
      "std_time": 0.0005357530381944444,
      "std_time_std": 2.2069651137468503e-05,
      "topk_time": 0.0018565389845106338,
      "topk_time_std": 2.5060833799536397e-05,
      "speedup": 0.2885762392625781,
      "time_ratio": 3.4652887658227853
    }
  ],
  "accuracy": [
    {
      "seq_len": 1024,
      "k": 8,
      "d_model": 512,
      "n_heads": 8,
      "batch_size": 1,
      "relative_error_mean": 5.38828125,
      "relative_error_std": 0.037597529423487396,
      "cosine_similarity_mean": 0.56376953125,
      "cosine_similarity_std": 0.0011388577919619726,
      "k_ratio": 0.0078125
    },
    {
      "seq_len": 1024,
      "k": 16,
      "d_model": 512,
      "n_heads": 8,
      "batch_size": 1,
      "relative_error_mean": 3.829296875,
      "relative_error_std": 0.03361645308429713,
      "cosine_similarity_mean": 0.65810546875,
      "cosine_similarity_std": 0.002080788647720949,
      "k_ratio": 0.015625
    },
    {
      "seq_len": 1024,
      "k": 32,
      "d_model": 512,
      "n_heads": 8,
      "batch_size": 1,
      "relative_error_mean": 2.676171875,
      "relative_error_std": 0.029784996157356643,
      "cosine_similarity_mean": 0.74482421875,
      "cosine_similarity_std": 0.003661783839697788,
      "k_ratio": 0.03125
    },
    {
      "seq_len": 1024,
      "k": 64,
      "d_model": 512,
      "n_heads": 8,
      "batch_size": 1,
      "relative_error_mean": 1.800390625,
      "relative_error_std": 0.025334975072300002,
      "cosine_similarity_mean": 0.81640625,
      "cosine_similarity_std": 0.0017194157091463876,
      "k_ratio": 0.0625
    },
    {
      "seq_len": 1024,
      "k": 128,
      "d_model": 512,
      "n_heads": 8,
      "batch_size": 1,
      "relative_error_mean": 1.1953125,
      "relative_error_std": 0.008712776571560728,
      "cosine_similarity_mean": 0.87421875,
      "cosine_similarity_std": 0.001179984958358845,
      "k_ratio": 0.125
    },
    {
      "seq_len": 1024,
      "k": 256,
      "d_model": 512,
      "n_heads": 8,
      "batch_size": 1,
      "relative_error_mean": 0.759375,
      "relative_error_std": 0.005226206312601426,
      "cosine_similarity_mean": 0.9115234375,
      "cosine_similarity_std": 0.0007176239480810092,
      "k_ratio": 0.25
    },
    {
      "seq_len": 2048,
      "k": 8,
      "d_model": 512,
      "n_heads": 8,
      "batch_size": 1,
      "relative_error_mean": 6.5625,
      "relative_error_std": 0.07104651590243535,
      "cosine_similarity_mean": 0.51728515625,
      "cosine_similarity_std": 0.0029068117316674255,
      "k_ratio": 0.00390625
    },
    {
      "seq_len": 2048,
      "k": 16,
      "d_model": 512,
      "n_heads": 8,
      "batch_size": 1,
      "relative_error_mean": 4.7140625,
      "relative_error_std": 0.05137275694616748,
      "cosine_similarity_mean": 0.6173828125,
      "cosine_similarity_std": 0.002613103156300713,
      "k_ratio": 0.0078125
    },
    {
      "seq_len": 2048,
      "k": 32,
      "d_model": 512,
      "n_heads": 8,
      "batch_size": 1,
      "relative_error_mean": 3.3359375,
      "relative_error_std": 0.023109686652732876,
      "cosine_similarity_mean": 0.7125,
      "cosine_similarity_std": 0.0013246738248291541,
      "k_ratio": 0.015625
    },
    {
      "seq_len": 2048,
      "k": 64,
      "d_model": 512,
      "n_heads": 8,
      "batch_size": 1,
      "relative_error_mean": 2.3625,
      "relative_error_std": 0.019476485722371734,
      "cosine_similarity_mean": 0.79501953125,
      "cosine_similarity_std": 0.001324673824829154,
      "k_ratio": 0.03125
    },
    {
      "seq_len": 2048,
      "k": 128,
      "d_model": 512,
      "n_heads": 8,
      "batch_size": 1,
      "relative_error_mean": 1.65,
      "relative_error_std": 0.006976785585738966,
      "cosine_similarity_mean": 0.86298828125,
      "cosine_similarity_std": 0.001096188687531428,
      "k_ratio": 0.0625
    },
    {
      "seq_len": 2048,
      "k": 256,
      "d_model": 512,
      "n_heads": 8,
      "batch_size": 1,
      "relative_error_mean": 1.1203125,
      "relative_error_std": 0.009695057535930357,
      "cosine_similarity_mean": 0.90927734375,
      "cosine_similarity_std": 0.0013601941676937616,
      "k_ratio": 0.125
    },
    {
      "seq_len": 4096,
      "k": 8,
      "d_model": 512,
      "n_heads": 8,
      "batch_size": 1,
      "relative_error_mean": 7.5359375,
      "relative_error_std": 0.04267656338671144,
      "cosine_similarity_mean": 0.48056640625,
      "cosine_similarity_std": 0.001784733093993854,
      "k_ratio": 0.001953125
    },
    {
      "seq_len": 4096,
      "k": 16,
      "d_model": 512,
      "n_heads": 8,
      "batch_size": 1,
      "relative_error_mean": 5.446875,
      "relative_error_std": 0.029085172607791074,
      "cosine_similarity_mean": 0.58369140625,
      "cosine_similarity_std": 0.0011388577919619726,
      "k_ratio": 0.00390625
    },
    {
      "seq_len": 4096,
      "k": 32,
      "d_model": 512,
      "n_heads": 8,
      "batch_size": 1,
      "relative_error_mean": 3.949609375,
      "relative_error_std": 0.017178619865075018,
      "cosine_similarity_mean": 0.68359375,
      "cosine_similarity_std": 0.0013810679320049757,
      "k_ratio": 0.0078125
    },
    {
      "seq_len": 4096,
      "k": 64,
      "d_model": 512,
      "n_heads": 8,
      "batch_size": 1,
      "relative_error_mean": 2.8578125,
      "relative_error_std": 0.01753031693149756,
      "cosine_similarity_mean": 0.777734375,
      "cosine_similarity_std": 0.0015563845166512917,
      "k_ratio": 0.015625
    },
    {
      "seq_len": 4096,
      "k": 128,
      "d_model": 512,
      "n_heads": 8,
      "batch_size": 1,
      "relative_error_mean": 2.07578125,
      "relative_error_std": 0.009679306010440522,
      "cosine_similarity_mean": 0.85087890625,
      "cosine_similarity_std": 0.0012955565587325782,
      "k_ratio": 0.03125
    },
    {
      "seq_len": 4096,
      "k": 256,
      "d_model": 512,
      "n_heads": 8,
      "batch_size": 1,
      "relative_error_mean": 1.495703125,
      "relative_error_std": 0.005262575619260734,
      "cosine_similarity_mean": 0.90625,
      "cosine_similarity_std": 0.0010697706201272775,
      "k_ratio": 0.0625
    },
    {
      "seq_len": 8192,
      "k": 8,
      "d_model": 512,
      "n_heads": 8,
      "batch_size": 1,
      "relative_error_mean": 8.1921875,
      "relative_error_std": 0.013621559198564604,
      "cosine_similarity_mean": 0.45478515625,
      "cosine_similarity_std": 0.0007307924583542854,
      "k_ratio": 0.0009765625
    },
    {
      "seq_len": 8192,
      "k": 16,
      "d_model": 512,
      "n_heads": 8,
      "batch_size": 1,
      "relative_error_mean": 5.953125,
      "relative_error_std": 0.01581910682134108,
      "cosine_similarity_mean": 0.5576171875,
      "cosine_similarity_std": 0.0010242273907911637,
      "k_ratio": 0.001953125
    },
    {
      "seq_len": 8192,
      "k": 32,
      "d_model": 512,
      "n_heads": 8,
      "batch_size": 1,
      "relative_error_mean": 4.36640625,
      "relative_error_std": 0.0129319885603491,
      "cosine_similarity_mean": 0.66435546875,
      "cosine_similarity_std": 0.0012955565587325782,
      "k_ratio": 0.00390625
    },
    {
      "seq_len": 8192,
      "k": 64,
      "d_model": 512,
      "n_heads": 8,
      "batch_size": 1,
      "relative_error_mean": 3.23125,
      "relative_error_std": 0.008958863235296653,
      "cosine_similarity_mean": 0.76259765625,
      "cosine_similarity_std": 0.001171875,
      "k_ratio": 0.0078125
    },
    {
      "seq_len": 8192,
      "k": 128,
      "d_model": 512,
      "n_heads": 8,
      "batch_size": 1,
      "relative_error_mean": 2.42890625,
      "relative_error_std": 0.003405389799641151,
      "cosine_similarity_mean": 0.84453125,
      "cosine_similarity_std": 0.001051790001393458,
      "k_ratio": 0.015625
    },
    {
      "seq_len": 8192,
      "k": 256,
      "d_model": 512,
      "n_heads": 8,
      "batch_size": 1,
      "relative_error_mean": 1.834765625,
      "relative_error_std": 0.0018936249443032536,
      "cosine_similarity_mean": 0.90224609375,
      "cosine_similarity_std": 0.0009959022487485909,
      "k_ratio": 0.03125
    }
  ],
  "scaling": [
    {
      "seq_len": 256,
      "model_type": "standard",
      "k": 256,
      "d_model": 512,
      "n_heads": 8,
      "time": 0.03465676307678223,
      "memory": 5705.708984375,
      "theoretical_memory": 65536,
      "theoretical_time_complexity": "O(L\u00b2)"
    },
    {
      "seq_len": 256,
      "model_type": "topk",
      "k": 64,
      "d_model": 512,
      "n_heads": 8,
      "time": 0.010727882385253906,
      "memory": 5705.708984375,
      "theoretical_memory": 16384,
      "theoretical_time_complexity": "O(L\u00b7k)"
    },
    {
      "seq_len": 512,
      "model_type": "standard",
      "k": 512,
      "d_model": 512,
      "n_heads": 8,
      "time": 0.012635469436645508,
      "memory": 5705.708984375,
      "theoretical_memory": 262144,
      "theoretical_time_complexity": "O(L\u00b2)"
    },
    {
      "seq_len": 512,
      "model_type": "topk",
      "k": 64,
      "d_model": 512,
      "n_heads": 8,
      "time": 0.01594829559326172,
      "memory": 5705.708984375,
      "theoretical_memory": 32768,
      "theoretical_time_complexity": "O(L\u00b7k)"
    },
    {
      "seq_len": 1024,
      "model_type": "standard",
      "k": 1024,
      "d_model": 512,
      "n_heads": 8,
      "time": 0.005944728851318359,
      "memory": 5705.708984375,
      "theoretical_memory": 1048576,
      "theoretical_time_complexity": "O(L\u00b2)"
    },
    {
      "seq_len": 1024,
      "model_type": "topk",
      "k": 64,
      "d_model": 512,
      "n_heads": 8,
      "time": 0.002204418182373047,
      "memory": 5705.708984375,
      "theoretical_memory": 65536,
      "theoretical_time_complexity": "O(L\u00b7k)"
    },
    {
      "seq_len": 2048,
      "model_type": "standard",
      "k": 2048,
      "d_model": 512,
      "n_heads": 8,
      "time": 0.00616002082824707,
      "memory": 5705.708984375,
      "theoretical_memory": 4194304,
      "theoretical_time_complexity": "O(L\u00b2)"
    },
    {
      "seq_len": 2048,
      "model_type": "topk",
      "k": 64,
      "d_model": 512,
      "n_heads": 8,
      "time": 0.007553577423095703,
      "memory": 5705.708984375,
      "theoretical_memory": 131072,
      "theoretical_time_complexity": "O(L\u00b7k)"
    },
    {
      "seq_len": 4096,
      "model_type": "standard",
      "k": 4096,
      "d_model": 512,
      "n_heads": 8,
      "time": 0.006367206573486328,
      "memory": 5705.708984375,
      "theoretical_memory": 16777216,
      "theoretical_time_complexity": "O(L\u00b2)"
    },
    {
      "seq_len": 4096,
      "model_type": "topk",
      "k": 64,
      "d_model": 512,
      "n_heads": 8,
      "time": 0.016675472259521484,
      "memory": 5705.708984375,
      "theoretical_memory": 262144,
      "theoretical_time_complexity": "O(L\u00b7k)"
    },
    {
      "seq_len": 8192,
      "model_type": "standard",
      "k": 8192,
      "d_model": 512,
      "n_heads": 8,
      "time": 0.008237838745117188,
      "memory": 6740.1328125,
      "theoretical_memory": 67108864,
      "theoretical_time_complexity": "O(L\u00b2)"
    },
    {
      "seq_len": 8192,
      "model_type": "topk",
      "k": 64,
      "d_model": 512,
      "n_heads": 8,
      "time": 0.00650787353515625,
      "memory": 6740.1328125,
      "theoretical_memory": 524288,
      "theoretical_time_complexity": "O(L\u00b7k)"
    }
  ]
}